adversarialattacknn/__init__.py
adversarialattacknn/aifgtm.py
adversarialattacknn/anda.py
adversarialattacknn/attack.py
adversarialattacknn/dta.py
adversarialattacknn/emifgsm.py
adversarialattacknn/fgsm.py
adversarialattacknn/gifgsm.py
adversarialattacknn/gnp.py
adversarialattacknn/gra.py
adversarialattacknn/iefgsm.py
adversarialattacknn/ifgsm.py
adversarialattacknn/ifgssm.py
adversarialattacknn/mifgsm.py
adversarialattacknn/mig.py
adversarialattacknn/model.py
adversarialattacknn/models.py
adversarialattacknn/ncs.py
adversarialattacknn/nifgsm.py
adversarialattacknn/pcifgsm.py
adversarialattacknn/pgn.py
adversarialattacknn/pifgsm.py
adversarialattacknn/rap.py
adversarialattacknn/smifgrm.py
adversarialattacknn/utils.py
adversarialattacknn/vaifgsm.py
adversarialattacknn/vmifgsm.py
adversarialattacknn/vnifgsm.py
adversarialattacknn-0.1.1.dist-info/METADATA
adversarialattacknn-0.1.1.dist-info/WHEEL
adversarialattacknn-0.1.1.dist-info/top_level.txt
adversarialattacknn-0.1.1.dist-info/RECORD
