Metadata-Version: 2.2
Name: adversarialattacknn
Version: 0.1.1
Summary: A library for adversarial attacks on neural networks
Home-page: https://github.com/santhosh1705kumar/adversarialattacknn
Author: Santhoshkumar K
Author-email: santhoshatwork17@gmail.com
Classifier: Programming Language :: Python :: 3
Classifier: License :: OSI Approved :: MIT License
Classifier: Operating System :: OS Independent
Requires-Python: >=3.6
Requires-Dist: torch>=1.7.0
Requires-Dist: timm>=0.4.0
Requires-Dist: numpy>=1.18.0
Requires-Dist: torchvision>=0.8.0
Dynamic: author
Dynamic: author-email
Dynamic: classifier
Dynamic: description
Dynamic: description-content-type
Dynamic: home-page
Dynamic: requires-dist
Dynamic: requires-python
Dynamic: summary
